codesecdirectapachtolgpl21/__init__.py
codesecdirectapachtolgpl21/module1.py
codesecdirectapachtolgpl21-0.1.0.dist-info/LICENSE
codesecdirectapachtolgpl21-0.1.0.dist-info/METADATA
codesecdirectapachtolgpl21-0.1.0.dist-info/WHEEL
codesecdirectapachtolgpl21-0.1.0.dist-info/top_level.txt
codesecdirectapachtolgpl21-0.1.0.dist-info/RECORD
