Metadata-Version: 2.1
Name: codesecdirectapachtolgpl21
Version: 0.1.0
Summary: A sample Python package
Author-email: Your Name <you@example.com>
License: Apache-2.0
Project-URL: Homepage, https://github.com/james-0131-2/pycodesecdirectapachtolgpl21
Project-URL: Repository, https://github.com/james-0131-2/pycodesecdirectapachtolgpl21
Requires-Python: >=3.7
License-File: LICENSE
Requires-Dist: requests
